we_pyutils/__init__.py
we_pyutils/env.py
we_pyutils/ip.py
we_pyutils/settings.py
we_pyutils/amazonaws/__init__.py
we_pyutils/amazonaws/ses.py
we_pyutils/amazonmws/__init__.py
we_pyutils/amazonmws/country.csv
we_pyutils/amazonmws/country.py
we_pyutils/decorators/__init__.py
we_pyutils/decorators/others.py
we_pyutils/django/__init__.py
we_pyutils/parsers/__init__.py
we_pyutils/parsers/ieee_ra.py
we_pyutils/proxy/__init__.py
we_pyutils/proxy/ty.py
we_pyutils/t/__init__.py
we_pyutils/t/amazon.py
we_pyutils/t/astasin.py
we_pyutils/t/file.py
we_pyutils/t/ip.py
we_pyutils/t/text.py
we_pyutils/t/aliyun/__init__.py
we_pyutils/t/aliyun/oss.py
we_pyutils/t/proxy/__init__.py
we_pyutils/t/proxy/ty.py
we_pyutils/t/proxy/ty_types.py
we_pyutils-0.2.13.dist-info/LICENSE
we_pyutils-0.2.13.dist-info/METADATA
we_pyutils-0.2.13.dist-info/WHEEL
we_pyutils-0.2.13.dist-info/top_level.txt
we_pyutils-0.2.13.dist-info/RECORD
