Metadata-Version: 2.1
Name: we-pyutils
Version: 0.2.13
Summary: WingEase Python Utils
Home-page: https://github.com/WingEase/we_pyutils
Author: ZENKR
Author-email: zenkr@qq.com
License: GPLv3
Keywords: pip,pyutils
Platform: UNKNOWN
Classifier: Programming Language :: Python :: 3
Requires-Python: >=3.8
License-File: LICENSE
Requires-Dist: requests
Requires-Dist: requests-toolbelt
Requires-Dist: Django
Requires-Dist: django-environ
Requires-Dist: oss2
